LICENSE
README.md
turboeda/__init__.py
turboeda/cli.py
turboeda/eda_report.py
turboeda/io_loader.py
turboeda/typerules.py
turboeda/analyzers/__init__.py
turboeda/analyzers/categorical.py
turboeda/analyzers/correlation.py
turboeda/analyzers/datetime.py
turboeda/analyzers/numeric.py
turboeda/analyzers/summary.py
turboeda/report/__init__.py
turboeda/report/renderer.py
turboeda/report/templates/base.html
turboeda/report/templates/sections/correlations.html
turboeda/report/templates/sections/summary.html
turboeda/report/templates/sections/variables.html
turboeda/viz/__init__.py
turboeda/viz/plots.py
turboeda-0.2.3.dist-info/METADATA
turboeda-0.2.3.dist-info/WHEEL
turboeda-0.2.3.dist-info/entry_points.txt
turboeda-0.2.3.dist-info/licenses/LICENSE
turboeda-0.2.3.dist-info/RECORD
