Metadata-Version: 2.4
Name: turboeda
Version: 0.2.3
Summary: One-command EDA report generator (HTML with Plotly).
Project-URL: Homepage, https://github.com/rozsit/turboeda
Project-URL: Documentation, https://github.com/rozsit/turboeda#readme
Project-URL: Source, https://github.com/rozsit/turboeda
Project-URL: Issues, https://github.com/rozsit/turboeda/issues
Project-URL: Changelog, https://github.com/rozsit/turboeda/releases
Author-email: Tamas Rozsahegyi <you@example.com>
License: MIT
License-File: LICENSE
Classifier: Development Status :: 4 - Beta
Classifier: Intended Audience :: Science/Research
Classifier: License :: OSI Approved :: MIT License
Classifier: Programming Language :: Python
Classifier: Programming Language :: Python :: 3
Classifier: Programming Language :: Python :: 3 :: Only
Classifier: Programming Language :: Python :: 3.9
Classifier: Programming Language :: Python :: 3.10
Classifier: Programming Language :: Python :: 3.11
Classifier: Programming Language :: Python :: 3.12
Classifier: Topic :: Scientific/Engineering :: Information Analysis
Requires-Python: >=3.9
Requires-Dist: chardet>=5.2
Requires-Dist: importlib-resources>=6.4; python_version < '3.11'
Requires-Dist: jinja2>=3.1
Requires-Dist: numpy>=1.25
Requires-Dist: openpyxl>=3.1
Requires-Dist: pandas>=2.0
Requires-Dist: plotly>=5.22
Requires-Dist: typer>=0.12
